[
    {   
        "name": "LinkedIn",
        "src": "../images/icons/linkedin.png",
        "external_url": "https://www.linkedin.com/henrique-batista/"
    },
    {   
        "name": "Github",
        "src": "../images/icons/github.png",
        "external_url": "https://www.linkedin.com/henrique-batista/"
    },
    {   
        "name": "email",
        "src": "../images/icons/email.png",
        "external_url": "https://www.linkedin.com/henrique-batista/"
    },
    {
       
        "name": "Flicker",
        "src": "../images/icons/flicker.png",
        "external_url": "https://www.linkedin.com/henrique-batista/"
    }
]